c4ddev/__init__.py
c4ddev/__main__.py
c4ddev/pypkg.py
c4ddev/res.py
c4ddev/resource.py
c4ddev/utils.py
c4ddev/ide/__init__.py
c4ddev/ide/gui.py
c4ddev/ide/script.py
c4ddev/ide/undotree.py
c4ddev/ide/utils.py
c4ddev/plugins/__init__.py
c4ddev/plugins/cli.py
c4ddev/plugins/ide.py
c4ddev/plugins/menu.py
c4ddev/plugins/pyobject.py
c4ddev/plugins/pyshader.py
c4ddev/plugins/scripting_server.py
c4ddev/plugins/uescape_tool.py
c4ddev/scripting/__init__.py
c4ddev/scripting/localimport.py
c4ddev-1.7.2.dist-info/LICENSE.txt
c4ddev-1.7.2.dist-info/METADATA
c4ddev-1.7.2.dist-info/WHEEL
c4ddev-1.7.2.dist-info/entry_points.txt
c4ddev-1.7.2.dist-info/top_level.txt
c4ddev-1.7.2.dist-info/zip-safe
c4ddev-1.7.2.dist-info/RECORD
