Metadata-Version: 2.1
Name: c4ddev
Version: 1.7.2
Summary: C4DDev is a set of command-line tools and Cinema 4D plugins to make development plugins easier.
Home-page: https://github.com/NiklasRosenstein/c4ddev
Author: Niklas Rosenstein
Author-email: rosensteinniklas@gmail.com
License: MIT
Platform: UNKNOWN
Requires-Dist: beautifulsoup4 (<5.0.0,>=4.6.0)
Requires-Dist: click (>=6.7.0)
Requires-Dist: nr.parsing.core (<0.1.0,>=0.0.1)
Requires-Dist: requests (<3.0.0,>=2.19.1)
Requires-Dist: six (<2.0.0,>=1.11.0)
